devpi_timemachine.py
devpi_timemachine-0.0.1.dist-info/LICENSE
devpi_timemachine-0.0.1.dist-info/METADATA
devpi_timemachine-0.0.1.dist-info/WHEEL
devpi_timemachine-0.0.1.dist-info/entry_points.txt
devpi_timemachine-0.0.1.dist-info/top_level.txt
devpi_timemachine-0.0.1.dist-info/RECORD
