Metadata-Version: 2.1
Name: devpi-timemachine
Version: 0.0.1
Summary: devpi-timemachine helps you manage your Python dependencies from a point in time in the past of your choosing
Home-page: https://github.com/jonafato/devpi-timemachine
Author: Jon Banafato
Author-email: pypi@jonafato.com
License: BSD 3-Clause License
Project-URL: Tracker, https://github.com/jonafato/devpi-timemachine/issues
Project-URL: Documentation, https://github.com/jonafato/devpi-timemachine/blob/main/README.md
Project-URL: Source, https://github.com/jonafato/devpi-timemachine
Classifier: Development Status :: 3 - Alpha
Classifier: Environment :: Plugins
Classifier: Intended Audience :: Developers
Classifier: License :: OSI Approved :: BSD License
Classifier: Programming Language :: Python
Classifier: Programming Language :: Python :: 3
Classifier: Programming Language :: Python :: 3.11
Classifier: Topic :: Software Development :: Libraries :: Python Modules
Classifier: Topic :: Software Development :: Quality Assurance
Requires-Python: >=3.11
License-File: LICENSE
Requires-Dist: devpi
Requires-Dist: packaging
Requires-Dist: pluggy
Requires-Dist: requests
